Workbook

Sheet Config
A1: Group Configuration
A3: Reporting Year | B3: 2025
A4: Currency | B4: EUR
A5: Tax Rate Domestic | B5: 0.25
A6: Tax Rate Foreign | B6: 0.3
A7: Transfer Pricing Markup | B7: 0.08
A8: Interco Interest Rate | B8: 0.04
A9: Depreciation Rate | B9: 0.1
A10: FX Rate USD/EUR | B10: 0.92
A11: FX Rate GBP/EUR | B11: 1.17
A12: Discount Rate (WACC) | B12: 0.09
A13: Dividend Payout Ratio | B13: 0.4
A14: Goodwill | B14: 50000
A16: Effective Group Tax | B16: =AVERAGE(B5,B6)
A17: After-tax Retention | B17: =1-B16

Sheet Entity_A
A1: Entity_A — Standalone Financials
A2: All amounts in local currency
A4: PROFIT & LOSS
A5: Item | B5: Q1 | C5: Q2 | D5: Q3 | E5: Q4 | F5: FY
A6: External Revenue | B6: 120000 | C6: 135000 | D6: 150000 | E6: 140000 | F6: =SUM(B6:E6)
A7: Intercompany Revenue | B7: 5000 | C7: 5000 | D7: 5000 | E7: 5000 | F7: =SUM(B7:E7)
A8: Total Revenue | B8: =B6+B7 | C8: =C6+C7 | D8: =D6+D7 | E8: =E6+E7 | F8: =SUM(B8:E8)
A9: COGS | B9: =B8*0.4 | C9: =C8*0.4 | D9: =D8*0.4 | E9: =E8*0.4 | F9: =SUM(B9:E9)
A10: Intercompany COGS | B10: 3000 | C10: 3000 | D10: 3000 | E10: 3000 | F10: =SUM(B10:E10)
A11: Personnel | B11: =B8*0.25 | C11: =C8*0.25 | D11: =D8*0.25 | E11: =E8*0.25 | F11: =SUM(B11:E11)
A12: Rent & Utilities | B12: =B8*0.05 | C12: =C8*0.05 | D12: =D8*0.05 | E12: =E8*0.05 | F12: =SUM(B12:E12)
A13: Marketing | B13: =B8*0.08 | C13: =C8*0.08 | D13: =D8*0.08 | E13: =E8*0.08 | F13: =SUM(B13:E13)
A14: Other OpEx | B14: =B8*0.04 | C14: =C8*0.04 | D14: =D8*0.04 | E14: =E8*0.04 | F14: =SUM(B14:E14)
A15: Total Costs | B15: =SUM(B9:B14) | C15: =SUM(C9:C14) | D15: =SUM(D9:D14) | E15: =SUM(E9:E14) | F15: =SUM(B15:E15)
A16: EBITDA | B16: =B8-B15 | C16: =C8-C15 | D16: =D8-D15 | E16: =E8-E15 | F16: =SUM(B16:E16)
A17: Depreciation | B17: =B8*Config!$B$9/4 | C17: =C8*Config!$B$9/4 | D17: =D8*Config!$B$9/4 | E17: =E8*Config!$B$9/4 | F17: =SUM(B17:E17)
A18: Intercompany Interest | B18: =20000*Config!$B$8/4 | C18: =20000*Config!$B$8/4 | D18: =20000*Config!$B$8/4 | E18: =20000*Config!$B$8/4 | F18: =SUM(B18:E18)
A19: EBT | B19: =B16-B17-B18 | C19: =C16-C17-C18 | D19: =D16-D17-D18 | E19: =E16-E17-E18 | F19: =SUM(B19:E19)
A20: Income Tax | B20: =IF(B19>0,B19*Config!$B$5,0) | C20: =IF(C19>0,C19*Config!$B$5,0) | D20: =IF(D19>0,D19*Config!$B$5,0) | E20: =IF(E19>0,E19*Config!$B$5,0) | F20: =SUM(B20:E20)
A21: Net Income | B21: =B19-B20 | C21: =C19-C20 | D21: =D19-D20 | E21: =E19-E20 | F21: =SUM(B21:E21)
A22: EBITDA Margin | B22: =IF(B8>0,B16/B8,0) | C22: =IF(C8>0,C16/C8,0) | D22: =IF(D8>0,D16/D8,0) | E22: =IF(E8>0,E16/E8,0) | F22: =IF(F8>0,F16/F8,0)
A23: Net Margin | B23: =IF(B8>0,B21/B8,0) | C23: =IF(C8>0,C21/C8,0) | D23: =IF(D8>0,D21/D8,0) | E23: =IF(E8>0,E21/E8,0) | F23: =IF(F8>0,F21/F8,0)
A25: BALANCE SHEET
A26: Item | B26: Amount | C26: EUR Equivalent
A27: Cash | B27: 80000 | C27: =B27*1
A28: Receivables | B28: 45000 | C28: =B28*1
A29: Inventory | B29: 30000 | C29: =B29*1
A30: Intercompany Receivable | B30: 20000 | C30: =B30*1
A31: Fixed Assets (net) | B31: 200000 | C31: =B31*1
A32: Total Assets | B32: =SUM(B27:B31) | C32: =SUM(C27:C31)
A33: Payables | B33: 35000 | C33: =B33*1
A34: Intercompany Payable | B34: 0 | C34: =B34*1
A35: Debt | B35: 100000 | C35: =B35*1
A36: Equity | B36: =B32-SUM(B33:B35) | C36: =B36*1
A37: Total Liabilities + Equity | B37: =SUM(B33:B36) | C37: =SUM(C33:C36)
A38: Balance Check | B38: =IF(ABS(B32-B37)<0.01,"OK","ERROR")

Sheet Entity_B
A1: Entity_B — Standalone Financials
A2: All amounts in local currency
A4: PROFIT & LOSS
A5: Item | B5: Q1 | C5: Q2 | D5: Q3 | E5: Q4 | F5: FY
A6: External Revenue | B6: 95000 | C6: 110000 | D6: 105000 | E6: 120000 | F6: =SUM(B6:E6)
A7: Intercompany Revenue | B7: 3000 | C7: 3000 | D7: 3000 | E7: 3000 | F7: =SUM(B7:E7)
A8: Total Revenue | B8: =B6+B7 | C8: =C6+C7 | D8: =D6+D7 | E8: =E6+E7 | F8: =SUM(B8:E8)
A9: COGS | B9: =B8*0.38 | C9: =C8*0.38 | D9: =D8*0.38 | E9: =E8*0.38 | F9: =SUM(B9:E9)
A10: Intercompany COGS | B10: 5000 | C10: 5000 | D10: 5000 | E10: 5000 | F10: =SUM(B10:E10)
A11: Personnel | B11: =B8*0.28 | C11: =C8*0.28 | D11: =D8*0.28 | E11: =E8*0.28 | F11: =SUM(B11:E11)
A12: Rent & Utilities | B12: =B8*0.06 | C12: =C8*0.06 | D12: =D8*0.06 | E12: =E8*0.06 | F12: =SUM(B12:E12)
A13: Marketing | B13: =B8*0.1 | C13: =C8*0.1 | D13: =D8*0.1 | E13: =E8*0.1 | F13: =SUM(B13:E13)
A14: Other OpEx | B14: =B8*0.05 | C14: =C8*0.05 | D14: =D8*0.05 | E14: =E8*0.05 | F14: =SUM(B14:E14)
A15: Total Costs | B15: =SUM(B9:B14) | C15: =SUM(C9:C14) | D15: =SUM(D9:D14) | E15: =SUM(E9:E14) | F15: =SUM(B15:E15)
A16: EBITDA | B16: =B8-B15 | C16: =C8-C15 | D16: =D8-D15 | E16: =E8-E15 | F16: =SUM(B16:E16)
A17: Depreciation | B17: =B8*Config!$B$9/4 | C17: =C8*Config!$B$9/4 | D17: =D8*Config!$B$9/4 | E17: =E8*Config!$B$9/4 | F17: =SUM(B17:E17)
A18: Intercompany Interest | B18: =-20000*Config!$B$8/4 | C18: =-20000*Config!$B$8/4 | D18: =-20000*Config!$B$8/4 | E18: =-20000*Config!$B$8/4 | F18: =SUM(B18:E18)
A19: EBT | B19: =B16-B17-B18 | C19: =C16-C17-C18 | D19: =D16-D17-D18 | E19: =E16-E17-E18 | F19: =SUM(B19:E19)
A20: Income Tax | B20: =IF(B19>0,B19*Config!$B$6,0) | C20: =IF(C19>0,C19*Config!$B$6,0) | D20: =IF(D19>0,D19*Config!$B$6,0) | E20: =IF(E19>0,E19*Config!$B$6,0) | F20: =SUM(B20:E20)
A21: Net Income | B21: =B19-B20 | C21: =C19-C20 | D21: =D19-D20 | E21: =E19-E20 | F21: =SUM(B21:E21)
A22: EBITDA Margin | B22: =IF(B8>0,B16/B8,0) | C22: =IF(C8>0,C16/C8,0) | D22: =IF(D8>0,D16/D8,0) | E22: =IF(E8>0,E16/E8,0) | F22: =IF(F8>0,F16/F8,0)
A23: Net Margin | B23: =IF(B8>0,B21/B8,0) | C23: =IF(C8>0,C21/C8,0) | D23: =IF(D8>0,D21/D8,0) | E23: =IF(E8>0,E21/E8,0) | F23: =IF(F8>0,F21/F8,0)
A25: BALANCE SHEET
A26: Item | B26: Amount | C26: EUR Equivalent
A27: Cash | B27: 60000 | C27: =B27*Config!$B$10
A28: Receivables | B28: 35000 | C28: =B28*Config!$B$10
A29: Inventory | B29: 25000 | C29: =B29*Config!$B$10
A30: Intercompany Receivable | B30: 0 | C30: =B30*Config!$B$10
A31: Fixed Assets (net) | B31: 150000 | C31: =B31*Config!$B$10
A32: Total Assets | B32: =SUM(B27:B31) | C32: =SUM(C27:C31)
A33: Payables | B33: 28000 | C33: =B33*Config!$B$10
A34: Intercompany Payable | B34: 20000 | C34: =B34*Config!$B$10
A35: Debt | B35: 80000 | C35: =B35*Config!$B$10
A36: Equity | B36: =B32-SUM(B33:B35) | C36: =B36*Config!$B$10
A37: Total Liabilities + Equity | B37: =SUM(B33:B36) | C37: =SUM(C33:C36)
A38: Balance Check | B38: =IF(ABS(B32-B37)<0.01,"OK","ERROR")

Sheet Entity_C
A1: Entity_C — Standalone Financials
A2: All amounts in local currency
A4: PROFIT & LOSS
A5: Item | B5: Q1 | C5: Q2 | D5: Q3 | E5: Q4 | F5: FY
A6: External Revenue | B6: 65000 | C6: 72000 | D6: 80000 | E6: 75000 | F6: =SUM(B6:E6)
A7: Intercompany Revenue | B7: 0 | C7: 0 | D7: 0 | E7: 0 | F7: =SUM(B7:E7)
A8: Total Revenue | B8: =B6+B7 | C8: =C6+C7 | D8: =D6+D7 | E8: =E6+E7 | F8: =SUM(B8:E8)
A9: COGS | B9: =B8*0.42 | C9: =C8*0.42 | D9: =D8*0.42 | E9: =E8*0.42 | F9: =SUM(B9:E9)
A10: Intercompany COGS | B10: 0 | C10: 0 | D10: 0 | E10: 0 | F10: =SUM(B10:E10)
A11: Personnel | B11: =B8*0.22 | C11: =C8*0.22 | D11: =D8*0.22 | E11: =E8*0.22 | F11: =SUM(B11:E11)
A12: Rent & Utilities | B12: =B8*0.04 | C12: =C8*0.04 | D12: =D8*0.04 | E12: =E8*0.04 | F12: =SUM(B12:E12)
A13: Marketing | B13: =B8*0.06 | C13: =C8*0.06 | D13: =D8*0.06 | E13: =E8*0.06 | F13: =SUM(B13:E13)
A14: Other OpEx | B14: =B8*0.03 | C14: =C8*0.03 | D14: =D8*0.03 | E14: =E8*0.03 | F14: =SUM(B14:E14)
A15: Total Costs | B15: =SUM(B9:B14) | C15: =SUM(C9:C14) | D15: =SUM(D9:D14) | E15: =SUM(E9:E14) | F15: =SUM(B15:E15)
A16: EBITDA | B16: =B8-B15 | C16: =C8-C15 | D16: =D8-D15 | E16: =E8-E15 | F16: =SUM(B16:E16)
A17: Depreciation | B17: =B8*Config!$B$9/4 | C17: =C8*Config!$B$9/4 | D17: =D8*Config!$B$9/4 | E17: =E8*Config!$B$9/4 | F17: =SUM(B17:E17)
A18: Intercompany Interest | B18: =0*Config!$B$8/4 | C18: =0*Config!$B$8/4 | D18: =0*Config!$B$8/4 | E18: =0*Config!$B$8/4 | F18: =SUM(B18:E18)
A19: EBT | B19: =B16-B17-B18 | C19: =C16-C17-C18 | D19: =D16-D17-D18 | E19: =E16-E17-E18 | F19: =SUM(B19:E19)
A20: Income Tax | B20: =IF(B19>0,B19*Config!$B$6,0) | C20: =IF(C19>0,C19*Config!$B$6,0) | D20: =IF(D19>0,D19*Config!$B$6,0) | E20: =IF(E19>0,E19*Config!$B$6,0) | F20: =SUM(B20:E20)
A21: Net Income | B21: =B19-B20 | C21: =C19-C20 | D21: =D19-D20 | E21: =E19-E20 | F21: =SUM(B21:E21)
A22: EBITDA Margin | B22: =IF(B8>0,B16/B8,0) | C22: =IF(C8>0,C16/C8,0) | D22: =IF(D8>0,D16/D8,0) | E22: =IF(E8>0,E16/E8,0) | F22: =IF(F8>0,F16/F8,0)
A23: Net Margin | B23: =IF(B8>0,B21/B8,0) | C23: =IF(C8>0,C21/C8,0) | D23: =IF(D8>0,D21/D8,0) | E23: =IF(E8>0,E21/E8,0) | F23: =IF(F8>0,F21/F8,0)
A25: BALANCE SHEET
A26: Item | B26: Amount | C26: EUR Equivalent
A27: Cash | B27: 40000 | C27: =B27*Config!$B$11
A28: Receivables | B28: 22000 | C28: =B28*Config!$B$11
A29: Inventory | B29: 18000 | C29: =B29*Config!$B$11
A30: Intercompany Receivable | B30: 0 | C30: =B30*Config!$B$11
A31: Fixed Assets (net) | B31: 120000 | C31: =B31*Config!$B$11
A32: Total Assets | B32: =SUM(B27:B31) | C32: =SUM(C27:C31)
A33: Payables | B33: 18000 | C33: =B33*Config!$B$11
A34: Intercompany Payable | B34: 0 | C34: =B34*Config!$B$11
A35: Debt | B35: 60000 | C35: =B35*Config!$B$11
A36: Equity | B36: =B32-SUM(B33:B35) | C36: =B36*Config!$B$11
A37: Total Liabilities + Equity | B37: =SUM(B33:B36) | C37: =SUM(C33:C36)
A38: Balance Check | B38: =IF(ABS(B32-B37)<0.01,"OK","ERROR")

Sheet Intercompany
A1: Intercompany Eliminations
A3: Item | B3: Entity From | C3: Entity To | D3: Amount (EUR) | E3: Elimination
A4: Interco Revenue A→B | B4: Entity_A | C4: Entity_B | D4: =Entity_A!F7 | E4: =D4
A5: Interco COGS B←A | B5: Entity_B | C5: Entity_A | D5: =Entity_B!F10*Config!$B$10 | E5: =D5
A7: Interco Loan A→B | B7: Entity_A | C7: Entity_B | D7: =Entity_A!B30 | E7: =D7
A8: Interco Loan B←A | B8: Entity_B | C8: Entity_A | D8: =Entity_B!B34*Config!$B$10 | E8: =D8
A10: Interco Interest A (income) | D10: =Entity_A!F18 | E10: =D10
A11: Interco Interest B (expense) | D11: =Entity_B!F18*Config!$B$10 | E11: =D11
A13: Total Revenue Elimination | D13: =D4
A14: Total Cost Elimination | D14: =D5
A15: Total Asset Elimination | D15: =D7
A16: Total Liability Elimination | D16: =D8
A17: Net Interest Elimination | D17: =D10+D11
A19: Revenue/COGS Match | D19: =IF(ABS(D13-D14)<1,"OK","MISMATCH")
A20: Loan Match | D20: =IF(ABS(D15-D16)<1,"OK","MISMATCH")

Sheet Consolidated
A1: Consolidated Group Financials
A2: All amounts in EUR
A4: CONSOLIDATED P&L
A5: Item | B5: Entity A | C5: Entity B (EUR) | D5: Entity C (EUR) | E5: Eliminations | F5: Consolidated
A6: Total Revenue | B6: =Entity_A!F8 | C6: =Entity_B!F8*Config!$B$10 | D6: =Entity_C!F8*Config!$B$11 | E6: =-Intercompany!D13 | F6: =SUM(B6:E6)
A7: External Revenue | B7: =Entity_A!F6 | C7: =Entity_B!F6*Config!$B$10 | D7: =Entity_C!F6*Config!$B$11 | E7: 0 | F7: =SUM(B7:E7)
A8: Total Costs | B8: =Entity_A!F15 | C8: =Entity_B!F15*Config!$B$10 | D8: =Entity_C!F15*Config!$B$11 | E8: =-Intercompany!D14 | F8: =SUM(B8:E8)
A9: EBITDA | B9: =Entity_A!F16 | C9: =Entity_B!F16*Config!$B$10 | D9: =Entity_C!F16*Config!$B$11 | E9: =E6-E8 | F9: =SUM(B9:E9)
A10: Depreciation | B10: =Entity_A!F17 | C10: =Entity_B!F17*Config!$B$10 | D10: =Entity_C!F17*Config!$B$11 | E10: 0 | F10: =SUM(B10:E10)
A11: Goodwill Amortization | E11: =Config!B14*Config!B9 | F11: =E11
A12: EBIT | F12: =F9-F10-F11
A13: Net Interest | B13: =Entity_A!F18 | C13: =Entity_B!F18*Config!$B$10 | D13: =Entity_C!F18*Config!$B$11 | E13: =-Intercompany!D17 | F13: =SUM(B13:E13)
A14: EBT | F14: =F12-F13
A15: Income Tax | B15: =Entity_A!F20 | C15: =Entity_B!F20*Config!$B$10 | D15: =Entity_C!F20*Config!$B$11 | E15: 0 | F15: =SUM(B15:E15)
A16: Net Income | F16: =F14-F15
A17: Dividends | F17: =IF(F16>0,F16*Config!$B$13,0)
A18: Retained Earnings | F18: =F16-F17
A20: CONSOLIDATED BALANCE SHEET
A21: Item | B21: Entity A | C21: Entity B (EUR) | D21: Entity C (EUR) | E21: Eliminations | F21: Consolidated
A22: Total Assets | B22: =Entity_A!B32 | C22: =Entity_B!C32 | D22: =Entity_C!C32 | E22: =-Intercompany!D15 | F22: =SUM(B22:E22)+Config!B14
A23: Total Liabilities + Equity | B23: =Entity_A!B37 | C23: =Entity_B!C37 | D23: =Entity_C!C37 | E23: =-Intercompany!D16 | F23: =SUM(B23:E23)+Config!B14
A24: Balance Check | F24: =IF(ABS(F22-F23)<1,"BALANCED","ERROR")

Sheet Ratios
A1: Financial Ratios — Consolidated
A3: Profitability
A4: Gross Margin | B4: =IF(Consolidated!F6>0,(Consolidated!F6-Consolidated!F8)/Consolidated!F6,0)
A5: EBITDA Margin | B5: =IF(Consolidated!F6>0,Consolidated!F9/Consolidated!F6,0)
A6: EBIT Margin | B6: =IF(Consolidated!F6>0,Consolidated!F12/Consolidated!F6,0)
A7: Net Margin | B7: =IF(Consolidated!F6>0,Consolidated!F16/Consolidated!F6,0)
A8: Return on Assets | B8: =IF(Consolidated!F22>0,Consolidated!F16/Consolidated!F22,0)
A10: Leverage
A11: Debt/Equity | B11: =IF((Consolidated!F23-Consolidated!F22+Consolidated!F23)>0,(Consolidated!F22-Consolidated!F23+Consolidated!F22)/Consolidated!F23,0)
A12: Asset Turnover | B12: =IF(Consolidated!F22>0,Consolidated!F6/Consolidated!F22,0)
A14: Growth & Efficiency
A15: Revenue per Entity | B15: =Consolidated!F7/3
A16: Cost Efficiency | B16: =IF(Consolidated!F6>0,Consolidated!F8/Consolidated!F6,0)
A18: Valuation
A19: EV/EBITDA | B19: =IF(Consolidated!F9>0,(Consolidated!F22+50000)/Consolidated!F9,0)
A20: Earnings Yield | B20: =IF(Consolidated!F22>0,Consolidated!F16/Consolidated!F22,0)
A22: Entity Comparison
A23: Entity | B23: Revenue (EUR) | C23: EBITDA (EUR) | D23: EBITDA Margin | E23: Share of Group
A24: Entity_A | B24: =Entity_A!F8*1 | C24: =Entity_A!F16*1 | D24: =IF(B24>0,C24/B24,0) | E24: =IF(Consolidated!F6>0,B24/Consolidated!F6,0)
A25: Entity_B | B25: =Entity_B!F8*Config!$B$10 | C25: =Entity_B!F16*Config!$B$10 | D25: =IF(B25>0,C25/B25,0) | E25: =IF(Consolidated!F6>0,B25/Consolidated!F6,0)
A26: Entity_C | B26: =Entity_C!F8*Config!$B$11 | C26: =Entity_C!F16*Config!$B$11 | D26: =IF(B26>0,C26/B26,0) | E26: =IF(Consolidated!F6>0,B26/Consolidated!F6,0)
A27: Check Sum | B27: =SUM(E24:E26)

Sheet Board
A1: Board of Directors Report
A3: Key Metrics
A4: Group Revenue | B4: =Consolidated!F6
A5: External Revenue | B5: =Consolidated!F7
A6: EBITDA | B6: =Consolidated!F9
A7: Net Income | B7: =Consolidated!F16
A8: Dividends | B8: =Consolidated!F17
A9: Retained Earnings | B9: =Consolidated!F18
A11: Margins
A12: Gross Margin | B12: =Ratios!B4
A13: EBITDA Margin | B13: =Ratios!B5
A14: Net Margin | B14: =Ratios!B7
A15: Return on Assets | B15: =Ratios!B8
A17: Balance Sheet
A18: Total Assets | B18: =Consolidated!F22
A19: Total L+E | B19: =Consolidated!F23
A20: Balance Status | B20: =Consolidated!F24
A22: Entity Performance
A23: Entity A | B23: =Ratios!B24 | C23: =Ratios!C24 | D23: =Ratios!D24 | E23: =Ratios!E24
A24: Entity B | B24: =Ratios!B25 | C24: =Ratios!C25 | D24: =Ratios!D25 | E24: =Ratios!E25
A25: Entity C | B25: =Ratios!B26 | C25: =Ratios!C26 | D25: =Ratios!D26 | E25: =Ratios!E26
A27: Valuation
A28: EV/EBITDA | B28: =Ratios!B19
A29: Earnings Yield | B29: =Ratios!B20
A31: Strategic Score | B31: =ROUND(B14*1000+B15*500+B28,1)
A32: Recommendation | B32: =IF(B31>200,"Strong Buy",IF(B31>100,"Buy",IF(B31>50,"Hold",IF(B31>0,"Underperform","Sell"))))
A34: Group Effective Tax Rate | B34: =IF(Consolidated!F14>0,Consolidated!F15/Consolidated!F14,0)
A35: Tax Efficiency vs Config | B35: =B34-Config!B16
A36: Tax Status | B36: =IF(ABS(B35)<0.02,"Aligned",IF(B35>0,"Over-taxed","Under-taxed"))
