Workbook

Sheet Suppliers
A1: SupplierID | B1: Name | C1: Country | D1: Lead Time (days) | E1: Reliability % | F1: Discount Tier
A2: SUP01 | B2: Acme Corp | C2: USA | D2: 7 | E2: 0.95 | F2: Gold
A3: SUP02 | B3: GlobalParts | C3: Germany | D3: 14 | E3: 0.92 | F3: Silver
A4: SUP03 | B4: EastMfg | C4: China | D4: 21 | E4: 0.88 | F4: Bronze
A5: SUP04 | B5: NordicSupply | C5: Sweden | D5: 10 | E5: 0.97 | F5: Gold
A6: SUP05 | B6: MediterraneanCo | C6: Italy | D6: 12 | E6: 0.9 | F6: Silver
A8: Avg Lead Time | B8: =AVERAGE(D2:D6)
A9: Avg Reliability | B9: =AVERAGE(E2:E6)
A10: Best Supplier | B10: =INDEX(B2:B6,MATCH(MAX(E2:E6),E2:E6,0))
A11: Gold Suppliers | B11: =COUNTIF(F2:F6,"Gold")

Sheet Catalog
A1: SKU | B1: Product | C1: Category | D1: SupplierID | E1: Unit Cost | F1: Markup % | G1: Sell Price | H1: Margin | I1: Supplier Lead Time | J1: Supplier Reliability
A2: SKU001 | B2: Widget Alpha | C2: Widgets | D2: SUP01 | E2: 12.5 | F2: 0.6 | G2: =ROUND(E2*(1+F2),2) | H2: =G2-E2 | I2: =IFERROR(INDEX(Suppliers!D:D,MATCH(D2,Suppliers!A:A,0)),"N/A") | J2: =IFERROR(INDEX(Suppliers!E:E,MATCH(D2,Suppliers!A:A,0)),0)
A3: SKU002 | B3: Widget Beta | C3: Widgets | D3: SUP01 | E3: 18 | F3: 0.55 | G3: =ROUND(E3*(1+F3),2) | H3: =G3-E3 | I3: =IFERROR(INDEX(Suppliers!D:D,MATCH(D3,Suppliers!A:A,0)),"N/A") | J3: =IFERROR(INDEX(Suppliers!E:E,MATCH(D3,Suppliers!A:A,0)),0)
A4: SKU003 | B4: Gadget Gamma | C4: Gadgets | D4: SUP02 | E4: 35 | F4: 0.45 | G4: =ROUND(E4*(1+F4),2) | H4: =G4-E4 | I4: =IFERROR(INDEX(Suppliers!D:D,MATCH(D4,Suppliers!A:A,0)),"N/A") | J4: =IFERROR(INDEX(Suppliers!E:E,MATCH(D4,Suppliers!A:A,0)),0)
A5: SKU004 | B5: Gadget Delta | C5: Gadgets | D5: SUP03 | E5: 28 | F5: 0.5 | G5: =ROUND(E5*(1+F5),2) | H5: =G5-E5 | I5: =IFERROR(INDEX(Suppliers!D:D,MATCH(D5,Suppliers!A:A,0)),"N/A") | J5: =IFERROR(INDEX(Suppliers!E:E,MATCH(D5,Suppliers!A:A,0)),0)
A6: SKU005 | B6: Tool Epsilon | C6: Tools | D6: SUP04 | E6: 55 | F6: 0.4 | G6: =ROUND(E6*(1+F6),2) | H6: =G6-E6 | I6: =IFERROR(INDEX(Suppliers!D:D,MATCH(D6,Suppliers!A:A,0)),"N/A") | J6: =IFERROR(INDEX(Suppliers!E:E,MATCH(D6,Suppliers!A:A,0)),0)
A7: SKU006 | B7: Tool Zeta | C7: Tools | D7: SUP02 | E7: 42 | F7: 0.42 | G7: =ROUND(E7*(1+F7),2) | H7: =G7-E7 | I7: =IFERROR(INDEX(Suppliers!D:D,MATCH(D7,Suppliers!A:A,0)),"N/A") | J7: =IFERROR(INDEX(Suppliers!E:E,MATCH(D7,Suppliers!A:A,0)),0)
A8: SKU007 | B8: Part Eta | C8: Parts | D8: SUP05 | E8: 8.5 | F8: 0.7 | G8: =ROUND(E8*(1+F8),2) | H8: =G8-E8 | I8: =IFERROR(INDEX(Suppliers!D:D,MATCH(D8,Suppliers!A:A,0)),"N/A") | J8: =IFERROR(INDEX(Suppliers!E:E,MATCH(D8,Suppliers!A:A,0)),0)
A9: SKU008 | B9: Part Theta | C9: Parts | D9: SUP03 | E9: 6 | F9: 0.75 | G9: =ROUND(E9*(1+F9),2) | H9: =G9-E9 | I9: =IFERROR(INDEX(Suppliers!D:D,MATCH(D9,Suppliers!A:A,0)),"N/A") | J9: =IFERROR(INDEX(Suppliers!E:E,MATCH(D9,Suppliers!A:A,0)),0)
A10: SKU009 | B10: Widget Iota | C10: Widgets | D10: SUP04 | E10: 22 | F10: 0.52 | G10: =ROUND(E10*(1+F10),2) | H10: =G10-E10 | I10: =IFERROR(INDEX(Suppliers!D:D,MATCH(D10,Suppliers!A:A,0)),"N/A") | J10: =IFERROR(INDEX(Suppliers!E:E,MATCH(D10,Suppliers!A:A,0)),0)
A11: SKU010 | B11: Gadget Kappa | C11: Gadgets | D11: SUP05 | E11: 40 | F11: 0.48 | G11: =ROUND(E11*(1+F11),2) | H11: =G11-E11 | I11: =IFERROR(INDEX(Suppliers!D:D,MATCH(D11,Suppliers!A:A,0)),"N/A") | J11: =IFERROR(INDEX(Suppliers!E:E,MATCH(D11,Suppliers!A:A,0)),0)
A12: SKU011 | B12: Tool Lambda | C12: Tools | D12: SUP01 | E12: 65 | F12: 0.38 | G12: =ROUND(E12*(1+F12),2) | H12: =G12-E12 | I12: =IFERROR(INDEX(Suppliers!D:D,MATCH(D12,Suppliers!A:A,0)),"N/A") | J12: =IFERROR(INDEX(Suppliers!E:E,MATCH(D12,Suppliers!A:A,0)),0)
A13: SKU012 | B13: Part Mu | C13: Parts | D13: SUP03 | E13: 4.5 | F13: 0.8 | G13: =ROUND(E13*(1+F13),2) | H13: =G13-E13 | I13: =IFERROR(INDEX(Suppliers!D:D,MATCH(D13,Suppliers!A:A,0)),"N/A") | J13: =IFERROR(INDEX(Suppliers!E:E,MATCH(D13,Suppliers!A:A,0)),0)
A15: Category | B15: Avg Cost | C15: Avg Sell | D15: Avg Margin | E15: Count
A16: Widgets | B16: =AVERAGEIF(C2:C13,A16,E2:E13) | C16: =AVERAGEIF(C2:C13,A16,G2:G13) | D16: =C16-B16 | E16: =COUNTIF(C2:C13,A16)
A17: Gadgets | B17: =AVERAGEIF(C2:C13,A17,E2:E13) | C17: =AVERAGEIF(C2:C13,A17,G2:G13) | D17: =C17-B17 | E17: =COUNTIF(C2:C13,A17)
A18: Tools | B18: =AVERAGEIF(C2:C13,A18,E2:E13) | C18: =AVERAGEIF(C2:C13,A18,G2:G13) | D18: =C18-B18 | E18: =COUNTIF(C2:C13,A18)
A19: Parts | B19: =AVERAGEIF(C2:C13,A19,E2:E13) | C19: =AVERAGEIF(C2:C13,A19,G2:G13) | D19: =C19-B19 | E19: =COUNTIF(C2:C13,A19)

Sheet Warehouse
A1: SKU | B1: On Hand | C1: Reorder Point | D1: Reorder Qty | E1: Unit Cost (from Catalog) | F1: Inventory Value | G1: Status | H1: Days of Supply | I1: Avg Daily Demand
A2: SKU001 | B2: 250 | C2: 50 | D2: 200 | E2: =INDEX(Catalog!E:E,MATCH(A2,Catalog!A:A,0)) | F2: =B2*E2 | G2: =IF(B2<=C2,"REORDER","OK") | H2: =IF(I2>0,ROUND(B2/I2,1),"N/A") | I2: 15
A3: SKU002 | B3: 30 | C3: 40 | D3: 150 | E3: =INDEX(Catalog!E:E,MATCH(A3,Catalog!A:A,0)) | F3: =B3*E3 | G3: =IF(B3<=C3,"REORDER","OK") | H3: =IF(I3>0,ROUND(B3/I3,1),"N/A") | I3: 12
A4: SKU003 | B4: 80 | C4: 25 | D4: 100 | E4: =INDEX(Catalog!E:E,MATCH(A4,Catalog!A:A,0)) | F4: =B4*E4 | G4: =IF(B4<=C4,"REORDER","OK") | H4: =IF(I4>0,ROUND(B4/I4,1),"N/A") | I4: 8
A5: SKU004 | B5: 120 | C5: 30 | D5: 100 | E5: =INDEX(Catalog!E:E,MATCH(A5,Catalog!A:A,0)) | F5: =B5*E5 | G5: =IF(B5<=C5,"REORDER","OK") | H5: =IF(I5>0,ROUND(B5/I5,1),"N/A") | I5: 10
A6: SKU005 | B6: 15 | C6: 20 | D6: 50 | E6: =INDEX(Catalog!E:E,MATCH(A6,Catalog!A:A,0)) | F6: =B6*E6 | G6: =IF(B6<=C6,"REORDER","OK") | H6: =IF(I6>0,ROUND(B6/I6,1),"N/A") | I6: 3
A7: SKU006 | B7: 60 | C7: 35 | D7: 80 | E7: =INDEX(Catalog!E:E,MATCH(A7,Catalog!A:A,0)) | F7: =B7*E7 | G7: =IF(B7<=C7,"REORDER","OK") | H7: =IF(I7>0,ROUND(B7/I7,1),"N/A") | I7: 7
A8: SKU007 | B8: 500 | C8: 100 | D8: 300 | E8: =INDEX(Catalog!E:E,MATCH(A8,Catalog!A:A,0)) | F8: =B8*E8 | G8: =IF(B8<=C8,"REORDER","OK") | H8: =IF(I8>0,ROUND(B8/I8,1),"N/A") | I8: 25
A9: SKU008 | B9: 800 | C9: 150 | D9: 500 | E9: =INDEX(Catalog!E:E,MATCH(A9,Catalog!A:A,0)) | F9: =B9*E9 | G9: =IF(B9<=C9,"REORDER","OK") | H9: =IF(I9>0,ROUND(B9/I9,1),"N/A") | I9: 40
A10: SKU009 | B10: 45 | C10: 30 | D10: 100 | E10: =INDEX(Catalog!E:E,MATCH(A10,Catalog!A:A,0)) | F10: =B10*E10 | G10: =IF(B10<=C10,"REORDER","OK") | H10: =IF(I10>0,ROUND(B10/I10,1),"N/A") | I10: 6
A11: SKU010 | B11: 20 | C11: 15 | D11: 60 | E11: =INDEX(Catalog!E:E,MATCH(A11,Catalog!A:A,0)) | F11: =B11*E11 | G11: =IF(B11<=C11,"REORDER","OK") | H11: =IF(I11>0,ROUND(B11/I11,1),"N/A") | I11: 4
A12: SKU011 | B12: 10 | C12: 10 | D12: 30 | E12: =INDEX(Catalog!E:E,MATCH(A12,Catalog!A:A,0)) | F12: =B12*E12 | G12: =IF(B12<=C12,"REORDER","OK") | H12: =IF(I12>0,ROUND(B12/I12,1),"N/A") | I12: 2
A13: SKU012 | B13: 1000 | C13: 200 | D13: 600 | E13: =INDEX(Catalog!E:E,MATCH(A13,Catalog!A:A,0)) | F13: =B13*E13 | G13: =IF(B13<=C13,"REORDER","OK") | H13: =IF(I13>0,ROUND(B13/I13,1),"N/A") | I13: 50
A15: Total Inventory Value | B15: =SUM(F2:F13)
A16: Items Below Reorder | B16: =COUNTIF(G2:G13,"REORDER")
A17: Reorder Value | B17: =SUMPRODUCT((B2:B13<=C2:C13)*D2:D13*E2:E13)
A18: Avg Days of Supply | B18: =IFERROR(AVERAGE(H2:H13),0)

Sheet Orders
A1: OrderID | B1: Date | C1: SKU | D1: Qty | E1: Sell Price (looked up) | F1: Unit Cost (looked up) | G1: Revenue | H1: COGS | I1: Gross Profit | J1: GP Margin | K1: Category
A2: ORD001 | B2: 45662 | C2: SKU001 | D2: 20 | E2: =INDEX(Catalog!G:G,MATCH(C2,Catalog!A:A,0)) | F2: =INDEX(Catalog!E:E,MATCH(C2,Catalog!A:A,0)) | G2: =D2*E2 | H2: =D2*F2 | I2: =G2-H2 | J2: =IF(G2>0,I2/G2,0) | K2: =INDEX(Catalog!C:C,MATCH(C2,Catalog!A:A,0))
A3: ORD002 | B3: 45665 | C3: SKU003 | D3: 5 | E3: =INDEX(Catalog!G:G,MATCH(C3,Catalog!A:A,0)) | F3: =INDEX(Catalog!E:E,MATCH(C3,Catalog!A:A,0)) | G3: =D3*E3 | H3: =D3*F3 | I3: =G3-H3 | J3: =IF(G3>0,I3/G3,0) | K3: =INDEX(Catalog!C:C,MATCH(C3,Catalog!A:A,0))
A4: ORD003 | B4: 45669 | C4: SKU007 | D4: 50 | E4: =INDEX(Catalog!G:G,MATCH(C4,Catalog!A:A,0)) | F4: =INDEX(Catalog!E:E,MATCH(C4,Catalog!A:A,0)) | G4: =D4*E4 | H4: =D4*F4 | I4: =G4-H4 | J4: =IF(G4>0,I4/G4,0) | K4: =INDEX(Catalog!C:C,MATCH(C4,Catalog!A:A,0))
A5: ORD004 | B5: 45672 | C5: SKU002 | D5: 15 | E5: =INDEX(Catalog!G:G,MATCH(C5,Catalog!A:A,0)) | F5: =INDEX(Catalog!E:E,MATCH(C5,Catalog!A:A,0)) | G5: =D5*E5 | H5: =D5*F5 | I5: =G5-H5 | J5: =IF(G5>0,I5/G5,0) | K5: =INDEX(Catalog!C:C,MATCH(C5,Catalog!A:A,0))
A6: ORD005 | B6: 45677 | C6: SKU005 | D6: 3 | E6: =INDEX(Catalog!G:G,MATCH(C6,Catalog!A:A,0)) | F6: =INDEX(Catalog!E:E,MATCH(C6,Catalog!A:A,0)) | G6: =D6*E6 | H6: =D6*F6 | I6: =G6-H6 | J6: =IF(G6>0,I6/G6,0) | K6: =INDEX(Catalog!C:C,MATCH(C6,Catalog!A:A,0))
A7: ORD006 | B7: 45679 | C7: SKU009 | D7: 10 | E7: =INDEX(Catalog!G:G,MATCH(C7,Catalog!A:A,0)) | F7: =INDEX(Catalog!E:E,MATCH(C7,Catalog!A:A,0)) | G7: =D7*E7 | H7: =D7*F7 | I7: =G7-H7 | J7: =IF(G7>0,I7/G7,0) | K7: =INDEX(Catalog!C:C,MATCH(C7,Catalog!A:A,0))
A8: ORD007 | B8: 45689 | C8: SKU004 | D8: 8 | E8: =INDEX(Catalog!G:G,MATCH(C8,Catalog!A:A,0)) | F8: =INDEX(Catalog!E:E,MATCH(C8,Catalog!A:A,0)) | G8: =D8*E8 | H8: =D8*F8 | I8: =G8-H8 | J8: =IF(G8>0,I8/G8,0) | K8: =INDEX(Catalog!C:C,MATCH(C8,Catalog!A:A,0))
A9: ORD008 | B9: 45693 | C9: SKU008 | D9: 100 | E9: =INDEX(Catalog!G:G,MATCH(C9,Catalog!A:A,0)) | F9: =INDEX(Catalog!E:E,MATCH(C9,Catalog!A:A,0)) | G9: =D9*E9 | H9: =D9*F9 | I9: =G9-H9 | J9: =IF(G9>0,I9/G9,0) | K9: =INDEX(Catalog!C:C,MATCH(C9,Catalog!A:A,0))
A10: ORD009 | B10: 45698 | C10: SKU006 | D10: 12 | E10: =INDEX(Catalog!G:G,MATCH(C10,Catalog!A:A,0)) | F10: =INDEX(Catalog!E:E,MATCH(C10,Catalog!A:A,0)) | G10: =D10*E10 | H10: =D10*F10 | I10: =G10-H10 | J10: =IF(G10>0,I10/G10,0) | K10: =INDEX(Catalog!C:C,MATCH(C10,Catalog!A:A,0))
A11: ORD010 | B11: 45702 | C11: SKU010 | D11: 4 | E11: =INDEX(Catalog!G:G,MATCH(C11,Catalog!A:A,0)) | F11: =INDEX(Catalog!E:E,MATCH(C11,Catalog!A:A,0)) | G11: =D11*E11 | H11: =D11*F11 | I11: =G11-H11 | J11: =IF(G11>0,I11/G11,0) | K11: =INDEX(Catalog!C:C,MATCH(C11,Catalog!A:A,0))
A12: ORD011 | B12: 45706 | C12: SKU001 | D12: 30 | E12: =INDEX(Catalog!G:G,MATCH(C12,Catalog!A:A,0)) | F12: =INDEX(Catalog!E:E,MATCH(C12,Catalog!A:A,0)) | G12: =D12*E12 | H12: =D12*F12 | I12: =G12-H12 | J12: =IF(G12>0,I12/G12,0) | K12: =INDEX(Catalog!C:C,MATCH(C12,Catalog!A:A,0))
A13: ORD012 | B13: 45710 | C13: SKU011 | D13: 2 | E13: =INDEX(Catalog!G:G,MATCH(C13,Catalog!A:A,0)) | F13: =INDEX(Catalog!E:E,MATCH(C13,Catalog!A:A,0)) | G13: =D13*E13 | H13: =D13*F13 | I13: =G13-H13 | J13: =IF(G13>0,I13/G13,0) | K13: =INDEX(Catalog!C:C,MATCH(C13,Catalog!A:A,0))
... A21: ORD020 | B21: 45752 | C21: SKU001 | D21: 25 | E21: =INDEX(Catalog!G:G,MATCH(C21,Catalog!A:A,0)) | F21: =INDEX(Catalog!E:E,MATCH(C21,Catalog!A:A,0)) | G21: =D21*E21 | H21: =D21*F21 | I21: =G21-H21 | J21: =IF(G21>0,I21/G21,0) | K21: =INDEX(Catalog!C:C,MATCH(C21,Catalog!A:A,0))
A24: Month | B24: Revenue | C24: COGS | D24: Gross Profit | E24: Orders
A25: Jan 2025 | B25: =SUM(G2:G6) | C25: =SUM(H2:H6) | D25: =B25-C25 | E25: =COUNTA(A2:A6)
A26: Feb 2025 | B26: =SUM(G8:G12) | C26: =SUM(H8:H12) | D26: =B26-C26 | E26: =COUNTA(A8:A12)
A27: Mar 2025 | B27: =SUM(G13:G18) | C27: =SUM(H13:H18) | D27: =B27-C27 | E27: =COUNTA(A13:A18)
A28: Apr 2025 | B28: =SUM(G19:G21) | C28: =SUM(H19:H21) | D28: =B28-C28 | E28: =COUNTA(A19:A21)
A30: Grand Total | B30: =SUM(B25:B28) | C30: =SUM(C25:C28) | D30: =B30-C30 | E30: =SUM(E25:E28)

Sheet Fulfillment
A1: Fulfillment Metrics
A3: Total Orders | B3: =Orders!E30
A4: Total Revenue | B4: =Orders!B30
A5: Total COGS | B5: =Orders!C30
A6: Gross Profit | B6: =B4-B5
A7: Gross Margin | B7: =IF(B4>0,B6/B4,0)
A9: Avg Order Value | B9: =IF(B3>0,B4/B3,0)
A10: Avg Profit per Order | B10: =IF(B3>0,B6/B3,0)
A12: Current Inventory Value | B12: =Warehouse!B15
A13: Items Needing Reorder | B13: =Warehouse!B16
A14: Reorder Cost | B14: =Warehouse!B17
A15: Inventory Turnover | B15: =IF(B12>0,B5/B12,0)
A17: Avg Supplier Lead Time | B17: =Suppliers!B8
A18: Avg Supplier Reliability | B18: =Suppliers!B9
A19: Best Supplier | B19: =Suppliers!B10
A21: Service Level Score | B21: =ROUND(B7*B18*100,1)
A22: Risk Assessment | B22: =IF(B13>3,"High Risk",IF(B13>1,"Medium Risk","Low Risk"))

Sheet Financials
A1: Financial Summary
A3: Revenue | B3: =Fulfillment!B4
A4: COGS | B4: =Fulfillment!B5
A5: Gross Profit | B5: =B3-B4
A6: Gross Margin | B6: =IF(B3>0,B5/B3,0)
A8: Operating Expenses | B8: =B3*0.20
A9: Reorder Costs (projected) | B9: =Fulfillment!B14
A10: EBITDA | B10: =B5-B8-B9
A11: Depreciation | B11: =Fulfillment!B12*0.1
A12: EBIT | B12: =B10-B11
A13: Tax (25%) | B13: =IF(B12>0,B12*0.25,0)
A14: Net Income | B14: =B12-B13
A15: Net Margin | B15: =IF(B3>0,B14/B3,0)
A17: Operating Cash Flow | B17: =B14+B11
A18: CapEx (Reorder) | B18: =-B9
A19: Free Cash Flow | B19: =B17+B18
A21: Inventory | B21: =Fulfillment!B12
A22: Working Capital Need | B22: =B21+B3*0.08

Sheet Executive
A1: Executive Dashboard
A3: Net Income | B3: =Financials!B14
A4: Free Cash Flow | B4: =Financials!B19
A5: Net Margin | B5: =Financials!B15
A6: Gross Margin | B6: =Financials!B6
A8: Revenue | B8: =Financials!B3
A9: Total Orders | B9: =Fulfillment!B3
A10: Avg Order Value | B10: =Fulfillment!B9
A12: Inventory Value | B12: =Fulfillment!B12
A13: Inventory Turnover | B13: =Fulfillment!B15
A14: Service Level | B14: =Fulfillment!B21
A16: Supply Chain Risk | B16: =Fulfillment!B22
A17: Best Supplier | B17: =Fulfillment!B19
A19: Profitability Score | B19: =ROUND(B5*100+B13*10+B14/10,1)
A20: Overall Grade | B20: =IF(B19>50,"Excellent",IF(B19>30,"Good",IF(B19>15,"Fair","Poor")))
A22: Monthly Revenue Trend
A23: =Orders!A25 | B23: =Orders!B25
A24: =Orders!A26 | B24: =Orders!B26 | C24: =IF(B23>0,(B24-B23)/B23,0)
A25: =Orders!A27 | B25: =Orders!B27 | C25: =IF(B24>0,(B25-B24)/B24,0)
A26: =Orders!A28 | B26: =Orders!B28 | C26: =IF(B25>0,(B26-B25)/B25,0)
A28: Avg Monthly Growth | B28: =IFERROR(AVERAGE(C24:C26),0)
