Workbook

Sheet Input
A1: Month | B1: Revenue | C1: Costs | D1: Profit
A2: Jan | B2: 12000 | C2: =B2*0.65 | D2: =B2-C2
A3: Feb | B3: 15000 | C3: =B3*0.62 | D3: =B3-C3
A4: Mar | B4: 13500 | C4: =B4*0.68 | D4: =B4-C4
A5: Apr | B5: 16000 | C5: =B5*0.6 | D5: =B5-C5
A6: May | B6: 18000 | C6: =B6*0.58 | D6: =B6-C6
A7: Jun | B7: 22000 | C7: =B7*0.55 | D7: =B7-C7
A8: Jul | B8: 25000 | C8: =B8*0.52 | D8: =B8-C8
A9: Aug | B9: 24000 | C9: =B9*0.54 | D9: =B9-C9
A10: Sep | B10: 20000 | C10: =B10*0.57 | D10: =B10-C10
A11: Oct | B11: 17000 | C11: =B11*0.61 | D11: =B11-C11
A12: Nov | B12: 14000 | C12: =B12*0.66 | D12: =B12-C12
A13: Dec | B13: 19000 | C13: =B13*0.59 | D13: =B13-C13
A14: Total | B14: =SUM(B2:B13) | C14: =SUM(C2:C13) | D14: =SUM(D2:D13)

Sheet Summary
A1: Annual Summary
A3: Total Revenue | B3: =Input!B14
A4: Total Costs | B4: =Input!C14
A5: Total Profit | B5: =Input!D14
A6: Profit Margin | B6: =B5/B3
A8: Avg Monthly Revenue | B8: =AVERAGE(Input!B2:Input!B13)
A9: Best Month Revenue | B9: =MAX(Input!B2:Input!B13)
A10: Worst Month Revenue | B10: =MIN(Input!B2:Input!B13)
A12: Profitable? | B12: =IF(B5>0,"Yes","No")
A13: Margin Status | B13: =IF(B6>0.3,"Healthy",IF(B6>0.15,"Moderate","Low"))
A14: Profit per Month | B14: =B5/12
