Workbook

Sheet Assumptions
A1: Financial Model Assumptions
A3: Growth Rate | B3: 0.08
A4: Tax Rate | B4: 0.25
A5: Inflation Rate | B5: 0.03
A6: Discount Rate | B6: 0.1
A7: Base Units | B7: 1000
A8: Unit Price | B8: 50
A9: Cost per Unit | B9: 30
A10: Fixed Costs | B10: 5000
A11: Depreciation Rate | B11: 0.15
A12: Initial Investment | B12: 100000
A13: Loan Rate | B13: 0.05
A14: Loan Term (years) | B14: 5
A16: Annual Payment | B16: =PMT(B13,B14,-B12)
A17: Effective Cost | B17: =B9*(1+B5)
A18: Break-even Units | B18: =ROUND(B10/(B8-B17),0)

Sheet Revenue
A1: Revenue Projections
A2: Item | B2: Year 1 | C2: Year 2 | D2: Year 3 | E2: Year 4 | F2: Year 5 | G2: Year 6 | H2: Year 7
A3: Units Sold | B3: =Assumptions!B7 | C3: =ROUND(B3*(1+Assumptions!$B$3),0) | D3: =ROUND(C3*(1+Assumptions!$B$3),0) | E3: =ROUND(D3*(1+Assumptions!$B$3),0) | F3: =ROUND(E3*(1+Assumptions!$B$3),0) | G3: =ROUND(F3*(1+Assumptions!$B$3),0) | H3: =ROUND(G3*(1+Assumptions!$B$3),0)
A4: Unit Price | B4: =Assumptions!B8 | C4: =B4*(1+Assumptions!$B$5) | D4: =C4*(1+Assumptions!$B$5) | E4: =D4*(1+Assumptions!$B$5) | F4: =E4*(1+Assumptions!$B$5) | G4: =F4*(1+Assumptions!$B$5) | H4: =G4*(1+Assumptions!$B$5)
A5: Gross Revenue | B5: =B3*B4 | C5: =C3*C4 | D5: =D3*D4 | E5: =E3*E4 | F5: =F3*F4 | G5: =G3*G4 | H5: =H3*H4
A7: Service Revenue | B7: 2000 | C7: =B7*1.05 | D7: =C7*1.05 | E7: =D7*1.05 | F7: =E7*1.05 | G7: =F7*1.05 | H7: =G7*1.05
A8: Total Revenue | B8: =B5+B7 | C8: =C5+C7 | D8: =D5+D7 | E8: =E5+E7 | F8: =F5+F7 | G8: =G5+G7 | H8: =H5+H7
A10: Cumulative Revenue | B10: =B8 | C10: =B10+C8 | D10: =C10+D8 | E10: =D10+E8 | F10: =E10+F8 | G10: =F10+G8 | H10: =G10+H8

Sheet Costs
A1: Cost Structure
A2: Item | B2: Year 1 | C2: Year 2 | D2: Year 3 | E2: Year 4 | F2: Year 5 | G2: Year 6 | H2: Year 7
A3: Variable Costs | B3: =Revenue!B3*Assumptions!$B$17 | C3: =Revenue!C3*Assumptions!$B$17 | D3: =Revenue!D3*Assumptions!$B$17 | E3: =Revenue!E3*Assumptions!$B$17 | F3: =Revenue!F3*Assumptions!$B$17 | G3: =Revenue!G3*Assumptions!$B$17 | H3: =Revenue!H3*Assumptions!$B$17
A4: Fixed Costs | B4: =Assumptions!B10 | C4: =B4*(1+Assumptions!$B$5) | D4: =C4*(1+Assumptions!$B$5) | E4: =D4*(1+Assumptions!$B$5) | F4: =E4*(1+Assumptions!$B$5) | G4: =F4*(1+Assumptions!$B$5) | H4: =G4*(1+Assumptions!$B$5)
A5: Depreciation | B5: =Assumptions!B12*Assumptions!B11 | C5: =MAX(B5-B5*Assumptions!$B$11, 0) | D5: =MAX(C5-C5*Assumptions!$B$11, 0) | E5: =MAX(D5-D5*Assumptions!$B$11, 0) | F5: =MAX(E5-E5*Assumptions!$B$11, 0) | G5: =MAX(F5-F5*Assumptions!$B$11, 0) | H5: =MAX(G5-G5*Assumptions!$B$11, 0)
A6: Loan Payment | B6: =IF(1<=Assumptions!$B$14,Assumptions!$B$16,0) | C6: =IF(2<=Assumptions!$B$14,Assumptions!$B$16,0) | D6: =IF(3<=Assumptions!$B$14,Assumptions!$B$16,0) | E6: =IF(4<=Assumptions!$B$14,Assumptions!$B$16,0) | F6: =IF(5<=Assumptions!$B$14,Assumptions!$B$16,0) | G6: =IF(6<=Assumptions!$B$14,Assumptions!$B$16,0) | H6: =IF(7<=Assumptions!$B$14,Assumptions!$B$16,0)
A8: Total Costs | B8: =SUM(B3:B6) | C8: =SUM(C3:C6) | D8: =SUM(D3:D6) | E8: =SUM(E3:E6) | F8: =SUM(F3:F6) | G8: =SUM(G3:G6) | H8: =SUM(H3:H6)
A10: Variable % of Revenue | B10: =IF(Revenue!B8>0,B3/Revenue!B8,0) | C10: =IF(Revenue!C8>0,C3/Revenue!C8,0) | D10: =IF(Revenue!D8>0,D3/Revenue!D8,0) | E10: =IF(Revenue!E8>0,E3/Revenue!E8,0) | F10: =IF(Revenue!F8>0,F3/Revenue!F8,0) | G10: =IF(Revenue!G8>0,G3/Revenue!G8,0) | H10: =IF(Revenue!H8>0,H3/Revenue!H8,0)

Sheet PnL
A1: Profit & Loss Statement
A2: Item | B2: Year 1 | C2: Year 2 | D2: Year 3 | E2: Year 4 | F2: Year 5 | G2: Year 6 | H2: Year 7
A3: Total Revenue | B3: =Revenue!B8 | C3: =Revenue!C8 | D3: =Revenue!D8 | E3: =Revenue!E8 | F3: =Revenue!F8 | G3: =Revenue!G8 | H3: =Revenue!H8
A4: Total Costs | B4: =Costs!B3+Costs!B4 | C4: =Costs!C3+Costs!C4 | D4: =Costs!D3+Costs!D4 | E4: =Costs!E3+Costs!E4 | F4: =Costs!F3+Costs!F4 | G4: =Costs!G3+Costs!G4 | H4: =Costs!H3+Costs!H4
A5: EBITDA | B5: =B3-B4 | C5: =C3-C4 | D5: =D3-D4 | E5: =E3-E4 | F5: =F3-F4 | G5: =G3-G4 | H5: =H3-H4
A6: Depreciation | B6: =Costs!B5 | C6: =Costs!C5 | D6: =Costs!D5 | E6: =Costs!E5 | F6: =Costs!F5 | G6: =Costs!G5 | H6: =Costs!H5
A7: EBIT | B7: =B5-B6 | C7: =C5-C6 | D7: =D5-D6 | E7: =E5-E6 | F7: =F5-F6 | G7: =G5-G6 | H7: =H5-H6
A8: Interest (Loan) | B8: =Costs!B6*Assumptions!$B$13 | C8: =Costs!C6*Assumptions!$B$13 | D8: =Costs!D6*Assumptions!$B$13 | E8: =Costs!E6*Assumptions!$B$13 | F8: =Costs!F6*Assumptions!$B$13 | G8: =Costs!G6*Assumptions!$B$13 | H8: =Costs!H6*Assumptions!$B$13
A9: EBT | B9: =B7-B8 | C9: =C7-C8 | D9: =D7-D8 | E9: =E7-E8 | F9: =F7-F8 | G9: =G7-G8 | H9: =H7-H8
A10: Tax | B10: =IF(B9>0,B9*Assumptions!$B$4,0) | C10: =IF(C9>0,C9*Assumptions!$B$4,0) | D10: =IF(D9>0,D9*Assumptions!$B$4,0) | E10: =IF(E9>0,E9*Assumptions!$B$4,0) | F10: =IF(F9>0,F9*Assumptions!$B$4,0) | G10: =IF(G9>0,G9*Assumptions!$B$4,0) | H10: =IF(H9>0,H9*Assumptions!$B$4,0)
A11: Net Income | B11: =B9-B10 | C11: =C9-C10 | D11: =D9-D10 | E11: =E9-E10 | F11: =F9-F10 | G11: =G9-G10 | H11: =H9-H10
A13: Cumulative Net Income | B13: =B11 | C13: =B13+C11 | D13: =C13+D11 | E13: =D13+E11 | F13: =E13+F11 | G13: =F13+G11 | H13: =G13+H11
A14: Net Margin | B14: =IF(B3>0,B11/B3,0) | C14: =IF(C3>0,C11/C3,0) | D14: =IF(D3>0,D11/D3,0) | E14: =IF(E3>0,E11/E3,0) | F14: =IF(F3>0,F11/F3,0) | G14: =IF(G3>0,G11/G3,0) | H14: =IF(H3>0,H11/H3,0)
A15: ROI | B15: =B13/Assumptions!$B$12 | C15: =C13/Assumptions!$B$12 | D15: =D13/Assumptions!$B$12 | E15: =E13/Assumptions!$B$12 | F15: =F13/Assumptions!$B$12 | G15: =G13/Assumptions!$B$12 | H15: =H13/Assumptions!$B$12

Sheet Analysis
A1: Financial Analysis
A3: 7-Year Total Revenue | B3: =SUM(PnL!B3:H3)
A4: 7-Year Total Net Income | B4: =SUM(PnL!B11:H11)
A5: Overall Margin | B5: =IF(B3>0,B4/B3,0)
A6: Final ROI | B6: =PnL!H15
A8: Avg Annual Revenue | B8: =AVERAGE(PnL!B3:H3)
A9: Revenue CAGR | B9: =IF(PnL!B3>0,(PnL!H3/PnL!B3)^(1/6)-1,0)
A11: Payback Status | B11: =IF(PnL!H13>=Assumptions!B12,"Recovered","Not Yet")
A13: NPV of Net Income | B13: =NPV(Assumptions!B6,PnL!B11:H11)
A14: Profitability Index | B14: =B13/Assumptions!B12
A16: Adjusted Margin | B16: =IF(B5>0.1,B5*0.95,B5*1.05)
A18: Investment Grade | B18: =IF(B14>1.5,"A",IF(B14>1,"B",IF(B14>0.5,"C","D")))
A20: Year | B20: Revenue Growth %
A21: Year 2 | B21: =IF(PnL!B3>0,(PnL!C3-PnL!B3)/PnL!B3,0)
A22: Year 3 | B22: =IF(PnL!C3>0,(PnL!D3-PnL!C3)/PnL!C3,0)
A23: Year 4 | B23: =IF(PnL!D3>0,(PnL!E3-PnL!D3)/PnL!D3,0)
A24: Year 5 | B24: =IF(PnL!E3>0,(PnL!F3-PnL!E3)/PnL!E3,0)
A25: Year 6 | B25: =IF(PnL!F3>0,(PnL!G3-PnL!F3)/PnL!F3,0)
A26: Year 7 | B26: =IF(PnL!G3>0,(PnL!H3-PnL!G3)/PnL!G3,0)
